square_authentication_helper/__init__.py
square_authentication_helper/main.py
square_authentication_helper/pydantic_models.py
square_authentication_helper-3.1.0.dist-info/WHEEL
square_authentication_helper-3.1.0.dist-info/METADATA
square_authentication_helper-3.1.0.dist-info/RECORD
