Metadata-Version: 2.3
Name: square_authentication_helper
Version: 3.1.0
Summary: helper to access the authentication layer for my personal server.
Keywords: authentication,helper,utilities
Author: Parth Mukesh Mangtani
Author-email: Parth Mukesh Mangtani <thepmsquare@gmail.com>
License: GPLv3
Classifier: Development Status :: 3 - Alpha
Classifier: Intended Audience :: Developers
Classifier: License :: OSI Approved :: GNU General Public License v3 (GPLv3)
Classifier: Programming Language :: Python :: 3
Classifier: Programming Language :: Python :: 3.12
Classifier: Programming Language :: Python :: 3 :: Only
Classifier: Topic :: Security
Classifier: Topic :: Software Development :: Libraries :: Python Modules
Requires-Dist: square-commons>=2.0.0
Requires-Dist: square-database-structure>=2.5.7
Requires-Python: >=3.12
Project-URL: homepage, https://github.com/thepmsquare/square_authentication_helper
